yt_fts/__init__.py
yt_fts/config.py
yt_fts/db_utils.py
yt_fts/download.py
yt_fts/embeddings.py
yt_fts/export.py
yt_fts/list.py
yt_fts/search.py
yt_fts/update.py
yt_fts/utils.py
yt_fts/vector_search.py
yt_fts/yt_fts.py
experimental_yt_fts-0.1.49.dist-info/LICENSE
experimental_yt_fts-0.1.49.dist-info/METADATA
experimental_yt_fts-0.1.49.dist-info/WHEEL
experimental_yt_fts-0.1.49.dist-info/entry_points.txt
experimental_yt_fts-0.1.49.dist-info/top_level.txt
experimental_yt_fts-0.1.49.dist-info/RECORD
