Metadata-Version: 2.1
Name: experimental-yt-fts
Version: 0.1.49
Summary: Search all of a YouTube channel from the command line
Author-email: NotJoeMartinez <notjoemartinez@protonmail.com>
License: This is free and unencumbered software released into the public domain.
Keywords: youtube,subtitles,search
Classifier: Programming Language :: Python :: 3
Classifier: License :: OSI Approved :: The Unlicense (Unlicense)
Classifier: Operating System :: OS Independent
Requires-Python: >=3.8
License-File: LICENSE
Requires-Dist: click ==8.1.7
Requires-Dist: openai ==1.4.0
Requires-Dist: chromadb ==0.4.20
Requires-Dist: requests ==2.31.0
Requires-Dist: rich ==13.7.0
Requires-Dist: sqlite-utils ==3.36
Requires-Dist: beautifulsoup4 ==4.12.2
